dwave_gate-0.3.4.dist-info/RECORD
dwave_gate-0.3.4.dist-info/WHEEL
dwave_gate-0.3.4.dist-info/top_level.txt
dwave_gate-0.3.4.dist-info/METADATA
dwave_gate-0.3.4.dist-info/licenses/LICENSE
dwave/gate/circuit.py
dwave/gate/primitives.py
dwave/gate/__init__.py
dwave/gate/mixedproperty.py
dwave/gate/tools/counters.py
dwave/gate/tools/unitary.py
dwave/gate/tools/__init__.py
dwave/gate/operations/__init__.py
dwave/gate/operations/operations.py
dwave/gate/operations/base.py
dwave/gate/registers/registers.py
dwave/gate/registers/cyregister.pxd
dwave/gate/registers/cyregister.cpp
dwave/gate/registers/cyregister.pyi
dwave/gate/registers/cyregister.cpython-310-darwin.so
dwave/gate/registers/__init__.py
dwave/gate/registers/cyregister.pyx
dwave/gate/simulator/ops.pxd
dwave/gate/simulator/simulator.cpp
dwave/gate/simulator/simulator.cpython-310-darwin.so
dwave/gate/simulator/__init__.py
dwave/gate/simulator/operation_generation.py
dwave/gate/simulator/ops.h
dwave/gate/simulator/simulator.pyx
dwave/gate/qir/compiler.py
dwave/gate/qir/instructions.py
dwave/gate/qir/__init__.py
dwave/gate/qir/loader.py
