Metadata-Version: 2.4
Name: dwave-gate
Version: 0.3.4
Summary: Gate model library.
Author-email: "D-Wave Inc." <tools@dwavesys.com>
License:                                  Apache License
Project-URL: Homepage, https://github.com/dwavesystems/dwave-gate
Project-URL: Download, https://github.com/dwavesystems/dwave-gate/releases
Classifier: Operating System :: Microsoft :: Windows
Classifier: Operating System :: POSIX
Classifier: Operating System :: Unix
Classifier: Operating System :: MacOS
Classifier: Programming Language :: Python
Classifier: Programming Language :: Python :: 3
Classifier: Programming Language :: Python :: 3.9
Classifier: Programming Language :: Python :: 3.10
Classifier: Programming Language :: Python :: 3.11
Classifier: Programming Language :: Python :: 3.12
Classifier: Programming Language :: Python :: 3.13
Classifier: Programming Language :: Python :: 3 :: Only
Requires-Python: >=3.9
License-File: LICENSE
Requires-Dist: numpy>=1.24.4
Provides-Extra: qir
Requires-Dist: pyqir<0.10,>=0.8.0; extra == "qir"
Dynamic: license-file
